histdata/__init__.py
histdata/api.py
histdata-1.1.dist-info/LICENSE
histdata-1.1.dist-info/METADATA
histdata-1.1.dist-info/WHEEL
histdata-1.1.dist-info/top_level.txt
histdata-1.1.dist-info/RECORD
