Metadata-Version: 2.1
Name: histdata
Version: 1.1
Summary: Download FX/commodities data (M1, Tick) from histdata.com.
Author: Philippe Remy
License: MIT
License-File: LICENSE
